file_organizer/__init__.py
file_organizer/cli.py
kps_file_organizer-0.3.0.dist-info/licenses/LICENSE
kps_file_organizer-0.3.0.dist-info/METADATA
kps_file_organizer-0.3.0.dist-info/WHEEL
kps_file_organizer-0.3.0.dist-info/entry_points.txt
kps_file_organizer-0.3.0.dist-info/top_level.txt
kps_file_organizer-0.3.0.dist-info/RECORD
