Metadata-Version: 2.4
Name: kps-file-organizer
Version: 0.3.0
Summary: A powerful and configurable command-line tool to organize your files effortlessly.
Author-email: Krishna Pratap Singh <kps369@proton.me>
Project-URL: Homepage, https://github.com/kps369/file-organizer
Project-URL: Bug Tracker, https://github.com/kps369/file-organizer/issues
Classifier: Programming Language :: Python :: 3
Classifier: License :: OSI Approved :: MIT License
Classifier: Operating System :: OS Independent
Requires-Python: >=3.8
License-File: LICENSE
Requires-Dist: typer
Requires-Dist: rich
Dynamic: license-file
